{
  "content": [
    {
      "title": "Recent work"
    }
  ],
  "projects": [
    {
      "title": "Kate & The Ink",
      "text": "E-commerce redesign and build",
      "link": "https://kateandtheink.com/",
      "linkText": "Visit website",
      "image": "/images/kateandtheink.jpg"
    },
    {
      "title": "5th Element Spaces",
      "text": "Branding, website design and build",
      "link": "https://www.fifthelementspaces.com/",
      "linkText": "Visit website",
      "image": "/images/fifthelement.jpg"
    },
    {
      "title": "Geoff's Fruit & Veg",
      "text": "Branding, website design and build",
      "link": "https://www.geoffsfruitandveg.co.uk/",
      "linkText": "Visit website",
      "image": "/images/geoffs.jpg"
    }
  ]
}